neis/__init__.py
neis/client.py
neis/domain.py
neis/meal.py
neis/school.py
pyneis-0.3.0.dist-info/METADATA
pyneis-0.3.0.dist-info/RECORD
pyneis-0.3.0.dist-info/WHEEL
pyneis-0.3.0.dist-info/top_level.txt
